z3c.flashmessage-3.1-py3.12-nspkg.pth
z3c/flashmessage/README.rst
z3c/flashmessage/TODO.txt
z3c/flashmessage/__init__.py
z3c/flashmessage/ftesting.zcml
z3c/flashmessage/interfaces.py
z3c/flashmessage/message.py
z3c/flashmessage/receiver.py
z3c/flashmessage/sketches.txt
z3c/flashmessage/sources.py
z3c/flashmessage/tests.py
z3c_flashmessage-3.1.dist-info/LICENSE.txt
z3c_flashmessage-3.1.dist-info/METADATA
z3c_flashmessage-3.1.dist-info/WHEEL
z3c_flashmessage-3.1.dist-info/namespace_packages.txt
z3c_flashmessage-3.1.dist-info/top_level.txt
z3c_flashmessage-3.1.dist-info/RECORD
