Metadata-Version: 2.2
Name: z3c.flashmessage
Version: 3.1
Summary: A package for sending `flash messages` to users.
Home-page: https://github.com/zopefoundation/z3c.flashmessage
Author: Jasper Op de Coul, Christian Theune
Author-email: jasper@infrae.com, mail@gocept.com
License: ZPL-2.1
Keywords: zope3 message zope session
Classifier: Environment :: Web Environment
Classifier: Intended Audience :: Developers
Classifier: License :: OSI Approved :: Zope Public License
Classifier: Programming Language :: Python :: 3
Classifier: Programming Language :: Python :: 3.9
Classifier: Programming Language :: Python :: 3.10
Classifier: Programming Language :: Python :: 3.11
Classifier: Programming Language :: Python :: 3.12
Classifier: Programming Language :: Python :: 3.13
Classifier: Programming Language :: Python :: Implementation :: CPython
Classifier: Programming Language :: Python :: Implementation :: PyPy
Classifier: Natural Language :: English
Classifier: Operating System :: OS Independent
Classifier: Topic :: Internet :: WWW/HTTP
Classifier: Framework :: Zope :: 3
Requires-Python: >=3.9
License-File: LICENSE.txt
Requires-Dist: setuptools
Requires-Dist: ZODB
Requires-Dist: zope.interface
Requires-Dist: zope.schema
Requires-Dist: zope.session
Provides-Extra: test
Requires-Dist: zope.publisher; extra == "test"
Requires-Dist: zope.component; extra == "test"
Requires-Dist: zope.security; extra == "test"
Requires-Dist: zope.testrunner; extra == "test"
Requires-Dist: zope.app.wsgi[testlayer]>=4.0; extra == "test"
Requires-Dist: Webtest; extra == "test"
Dynamic: author
Dynamic: author-email
Dynamic: classifier
Dynamic: description
Dynamic: home-page
Dynamic: keywords
Dynamic: license
Dynamic: provides-extra
Dynamic: requires-dist
Dynamic: requires-python
Dynamic: summary
